time_my_func/__init__.py
time_my_func/decorator.py
time_my_func-0.3.0.dist-info/licenses/LICENSE
time_my_func-0.3.0.dist-info/METADATA
time_my_func-0.3.0.dist-info/WHEEL
time_my_func-0.3.0.dist-info/top_level.txt
time_my_func-0.3.0.dist-info/RECORD
