Metadata-Version: 2.4
Name: time_my_func
Version: 0.3.0
Summary: A lightweight Python decorator to measure and print function execution time.
Author: Luca Paesano
License: MIT
Project-URL: Homepage, https://github.com/DeathlyDestiny/function_timer
Project-URL: Bug_Tracker, https://github.com/DeathlyDestiny/function_timer/issues
Keywords: timing,decorator,performance,benchmark
Classifier: Programming Language :: Python :: 3
Classifier: License :: OSI Approved :: MIT License
Classifier: Operating System :: OS Independent
Requires-Python: >=3.7
License-File: LICENSE
Provides-Extra: dev
Requires-Dist: pytest>=8.0; extra == "dev"
Requires-Dist: pytest-asyncio; extra == "dev"
Requires-Dist: build; extra == "dev"
Requires-Dist: twine; extra == "dev"
Dynamic: license-file
